kaboom/__init__.py
kablooey-0.0.1.dist-info/METADATA
kablooey-0.0.1.dist-info/WHEEL
kablooey-0.0.1.dist-info/top_level.txt
kablooey-0.0.1.dist-info/RECORD
