Metadata-Version: 2.1
Name: kablooey
Version: 0.0.1
Summary: Kaboom... in python. Original is in js
Home-page: https://kaboom-in-python.shivankchhaya.repl.co/site
Author: ShivC
Author-email: system.io64@gmail.com
License: UNKNOWN
Project-URL: Documentation, https://kaboom-in-python.shivankchhaya.repl.co/docs
Platform: UNKNOWN
Classifier: Programming Language :: Python :: 3
Classifier: License :: OSI Approved :: MIT License
Classifier: Operating System :: OS Independent
Requires-Python: >=3.8.2
